katsdpimageutils/__init__.py
katsdpimageutils/render.py
katsdpimageutils/zscale.py
katsdpimageutils/test/__init__.py
katsdpimageutils/test/test_zscale.py
katsdpimageutils-0.1.1.data/scripts/fits-image.py
katsdpimageutils-0.1.1.data/scripts/fits-video.py
katsdpimageutils-0.1.1.dist-info/LICENSE
katsdpimageutils-0.1.1.dist-info/METADATA
katsdpimageutils-0.1.1.dist-info/WHEEL
katsdpimageutils-0.1.1.dist-info/top_level.txt
katsdpimageutils-0.1.1.dist-info/RECORD
